ttotp/TinyProgress.py
ttotp/__init__.py
ttotp/__main__.py
ttotp/__version__.py
ttotp/sixel.py
textual_totp-0.9.6.dist-info/METADATA
textual_totp-0.9.6.dist-info/WHEEL
textual_totp-0.9.6.dist-info/entry_points.txt
textual_totp-0.9.6.dist-info/top_level.txt
textual_totp-0.9.6.dist-info/RECORD
