Metadata-Version: 2.4
Name: textual-totp
Version: 0.9.6
Summary: TOTP (authenticator) application using Python & Textual
Author-email: Jeff Epler <jepler@gmail.com>
Project-URL: homepage, https://codeberg.org/jepler/textual-totp
Project-URL: repository, https://codeberg.org/jepler/textual-totp
Keywords: otp,totp,2fa,authenticator
Classifier: Development Status :: 3 - Alpha
Classifier: License :: OSI Approved :: MIT License
Classifier: Operating System :: OS Independent
Classifier: Programming Language :: Python :: 3
Classifier: Programming Language :: Python :: 3.11
Classifier: Programming Language :: Python :: 3.12
Classifier: Programming Language :: Python :: Implementation :: CPython
Requires-Python: >=3.11
Requires-Dist: click
Requires-Dist: platformdirs
Requires-Dist: pyotp
Requires-Dist: pyperclip
Requires-Dist: qrcode
Requires-Dist: textual>=3.1.0
